busbar/__init__.py
busbar-0.1.0.dist-info/LICENSE
busbar-0.1.0.dist-info/METADATA
busbar-0.1.0.dist-info/WHEEL
busbar-0.1.0.dist-info/RECORD
